{
  "ItemCode": "",
  "ItemUrl": "https://ww1.cuevana3.me/54099/collider",
  "ItemTitle": " Collider",
  "ItemQty": "20",
  "ItemStatus": "",
  "BrandName": "",
  "ItemPrice": "",
  "ItemRetailPrice": "",
  "ShippingInfo": "",
  "StandardImage": "https://image.tmdb.org/t/p/w185_and_h278_bestv2/4VMHLhqxwtx3zbE7CmQE5mhUTAq.jpg",
  "OtherImages": "https://image.tmdb.org/t/p/w185_and_h278_bestv2/4VMHLhqxwtx3zbE7CmQE5mhUTAq.jpg",
  "ItemDescription": "En el a&#xF1;o 2033, una joven atrapada en un misterioso orfanato viaja imprudentemente hacia atr&#xE1;s en el tiempo para encontrar a sus padres y enmendar su pasado.",
  "ItemOption": {},
  "ItemOptionData": [],
  "ItemWeight": "",
  "ItemSize": "",
  "ItemExpiredate": "",
  "ISBNCode": "",
  "UPCCode": "",
  "ItemMFGdate": "",
  "ItemModelNo": "",
  "ItemMaterial": "",
  "Memo": "",
  "Category": ""
}